{
    "build": {
        "content": [
            {
                "files": [
                    "en/**.md",
                    "en/**/toc.yml"
                ],
                "exclude": ["obj/**", "_site/**"]
            }
        ],
        "resource": [
            {
                "files": [
                    "images/**",
                    "**/images/**",
                    "**/api/**",
                    "en/developer/archived-docs/**"
                ],
                "exclude": ["obj/**", "_site/**"]
            },
            {
                "files":[
                    "index.html",
                    "index.css"
                ]
            }
        ],
        "dest": "_site",
        "globalMetadataFiles": [],
        "fileMetadataFiles": [],
        "template": ["templates/reveal"],
        "noLangKeyword": false,
        "keepFileLink": false,
        "cleanupCacheHistory": false,
        "disableGitFeatures": true,
        "globalMetadata": {
            "_appTitle": "Reveal",
            "_navBarTitle": "Reveal",
            "_isLangEn": true,
            "_navBarTitleHref": "https://www.revealbi.io/",
            "_gtmContainerId": "GTM-P9F3PSS",
            "_gitContribute": {
              "repo": "https://github.com/RevealBi/Documentation",
              "branch": "master"
            }
        }
    }
}
